{
  "errors": [],
  "warnings": [],
  "version": "4.44.1",
  "hash": "f906e91cfe7f1a887486",
  "publicPath": "/static/",
  "outputPath": "C:\\Users\\User\\Desktop\\projects\\ip20\\build\\static",
  "assetsByChunkName": {
    "archive": "archive.module.js",
    "archive~post": "archive~post.module.js",
    "ip20": [
      "ip20.module.js",
      "ip20.01e945506d7bcbf70f53.hot-update.js"
    ],
    "post": "post.module.js"
  },
  "assets": [
    {
      "name": "01e945506d7bcbf70f53.hot-update.json",
      "size": 46,
      "chunks": [],
      "chunkNames": [],
      "info": {
        "hotModuleReplacement": true,
        "immutable": true
      },
      "emitted": false
    },
    {
      "name": "archive.module.js",
      "size": 74644,
      "chunks": [
        "archive"
      ],
      "chunkNames": [
        "archive"
      ],
      "info": {},
      "emitted": false
    },
    {
      "name": "archive~post.module.js",
      "size": 121355,
      "chunks": [
        "archive~post"
      ],
      "chunkNames": [
        "archive~post"
      ],
      "info": {},
      "emitted": false
    },
    {
      "name": "fonts/Inter-Bold-LATIN.woff2",
      "size": 33648,
      "chunks": [],
      "chunkNames": [],
      "info": {},
      "emitted": false
    },
    {
      "name": "fonts/Inter-Bold-US-ASCII.woff2",
      "size": 22248,
      "chunks": [],
      "chunkNames": [],
      "info": {},
      "emitted": false
    },
    {
      "name": "fonts/Inter-Bold.woff2",
      "size": 138872,
      "chunks": [],
      "chunkNames": [],
      "info": {},
      "emitted": false
    },
    {
      "name": "fonts/Inter-Medium-LATIN.woff2",
      "size": 33232,
      "chunks": [],
      "chunkNames": [],
      "info": {},
      "emitted": false
    },
    {
      "name": "fonts/Inter-Medium-US-ASCII.woff2",
      "size": 21828,
      "chunks": [],
      "chunkNames": [],
      "info": {},
      "emitted": false
    },
    {
      "name": "fonts/Inter-Medium.woff2",
      "size": 137268,
      "chunks": [],
      "chunkNames": [],
      "info": {},
      "emitted": false
    },
    {
      "name": "fonts/Inter-SemiBold-LATIN.woff2",
      "size": 33456,
      "chunks": [],
      "chunkNames": [],
      "info": {},
      "emitted": false
    },
    {
      "name": "fonts/Inter-SemiBold-US-ASCII.woff2",
      "size": 22032,
      "chunks": [],
      "chunkNames": [],
      "info": {},
      "emitted": false
    },
    {
      "name": "fonts/Inter-SemiBold.woff2",
      "size": 138088,
      "chunks": [],
      "chunkNames": [],
      "info": {},
      "emitted": false
    },
    {
      "name": "images/lines.png",
      "size": 5888,
      "chunks": [],
      "chunkNames": [],
      "info": {},
      "emitted": false
    },
    {
      "name": "images/logo.png",
      "size": 53320,
      "chunks": [],
      "chunkNames": [],
      "info": {},
      "emitted": false
    },
    {
      "name": "ip20.01e945506d7bcbf70f53.hot-update.js",
      "size": 2718,
      "chunks": [
        "ip20"
      ],
      "chunkNames": [
        "ip20"
      ],
      "info": {
        "hotModuleReplacement": true,
        "immutable": true
      },
      "emitted": false
    },
    {
      "name": "ip20.module.js",
      "size": 5855269,
      "chunks": [
        "ip20"
      ],
      "chunkNames": [
        "ip20"
      ],
      "info": {},
      "emitted": false
    },
    {
      "name": "post.module.js",
      "size": 30879,
      "chunks": [
        "post"
      ],
      "chunkNames": [
        "post"
      ],
      "info": {},
      "emitted": false
    }
  ],
  "filteredAssets": 0,
  "entrypoints": {
    "ip20": {
      "chunks": [
        "ip20"
      ],
      "assets": [
        "ip20.module.js",
        "ip20.01e945506d7bcbf70f53.hot-update.js"
      ],
      "children": {},
      "childAssets": {}
    }
  },
  "namedChunkGroups": {
    "ip20": {
      "chunks": [
        "ip20"
      ],
      "assets": [
        "ip20.module.js",
        "ip20.01e945506d7bcbf70f53.hot-update.js"
      ],
      "children": {},
      "childAssets": {}
    },
    "archive": {
      "chunks": [
        "archive~post",
        "archive"
      ],
      "assets": [
        "archive~post.module.js",
        "archive.module.js"
      ],
      "children": {},
      "childAssets": {}
    },
    "post": {
      "chunks": [
        "archive~post",
        "post"
      ],
      "assets": [
        "archive~post.module.js",
        "post.module.js"
      ],
      "children": {},
      "childAssets": {}
    }
  },
  "logging": {
    "webpack.buildChunkGraph.visitModules": {
      "entries": [],
      "filteredEntries": 5,
      "debug": false
    }
  },
  "children": []
}